easyeda/__init__.py
easyeda/eda.py
easyeda-2.0.dist-info/LICENSE
easyeda-2.0.dist-info/METADATA
easyeda-2.0.dist-info/WHEEL
easyeda-2.0.dist-info/top_level.txt
easyeda-2.0.dist-info/RECORD
