Metadata-Version: 2.1
Name: easyeda
Version: 2.0
Summary: A useful tool to Exploratory Data Analysis
Home-page: https://github.com/lyhue1991/easyeda
Author: PythonAiRoad
Author-email: lyhue1991@163.com
License: UNKNOWN
Platform: UNKNOWN
Classifier: Programming Language :: Python :: 3
Classifier: License :: OSI Approved :: MIT License
Classifier: Operating System :: OS Independent
Requires-Python: >=3.5
